scipy_openblas32/__init__.py
scipy_openblas32/__main__.py
scipy_openblas32/include/cblas.h
scipy_openblas32/include/f77blas.h
scipy_openblas32/include/lapack.h
scipy_openblas32/include/lapacke.h
scipy_openblas32/include/lapacke_config.h
scipy_openblas32/include/lapacke_mangling.h
scipy_openblas32/include/lapacke_utils.h
scipy_openblas32/include/openblas_config.h
scipy_openblas32/lib/libgfortran-daac5196.so.5.0.0
scipy_openblas32/lib/libscipy_openblas.so
scipy_openblas32/lib/cmake/openblas/OpenBLASConfig.cmake
scipy_openblas32/lib/cmake/openblas/OpenBLASConfigVersion.cmake
scipy_openblas32/lib/pkgconfig/scipy-openblas.pc
scipy_openblas32-0.3.31.22.1.dist-info/METADATA
scipy_openblas32-0.3.31.22.1.dist-info/WHEEL
scipy_openblas32-0.3.31.22.1.dist-info/entry_points.txt
scipy_openblas32-0.3.31.22.1.dist-info/top_level.txt
scipy_openblas32-0.3.31.22.1.dist-info/RECORD
scipy_openblas32-0.3.31.22.1.dist-info/licenses/LICENSE.txt
scipy_openblas32-0.3.31.22.1.dist-info/sboms/auditwheel.cdx.json
